piedomains/__init__.py
piedomains/api.py
piedomains/archive_org_downloader.py
piedomains/base.py
piedomains/config.py
piedomains/constants.py
piedomains/content_validation.py
piedomains/context_managers.py
piedomains/fetchers.py
piedomains/http_client.py
piedomains/piedomain.py
piedomains/piedomains_logging.py
piedomains/utils.py
piedomains/classifiers/__init__.py
piedomains/classifiers/combined_classifier.py
piedomains/classifiers/image_classifier.py
piedomains/classifiers/llm_classifier.py
piedomains/classifiers/text_classifier.py
piedomains/llm/__init__.py
piedomains/llm/config.py
piedomains/llm/prompts.py
piedomains/llm/response_parser.py
piedomains/model/calibrate/text/adv.sav
piedomains/model/calibrate/text/alcohol.sav
piedomains/model/calibrate/text/automobile.sav
piedomains/model/calibrate/text/dating.sav
piedomains/model/calibrate/text/downloads.sav
piedomains/model/calibrate/text/drugs.sav
piedomains/model/calibrate/text/education.sav
piedomains/model/calibrate/text/finance.sav
piedomains/model/calibrate/text/fortunetelling.sav
piedomains/model/calibrate/text/forum.sav
piedomains/model/calibrate/text/gamble.sav
piedomains/model/calibrate/text/government.sav
piedomains/model/calibrate/text/hobby.sav
piedomains/model/calibrate/text/hospitals.sav
piedomains/model/calibrate/text/imagehosting.sav
piedomains/model/calibrate/text/isp.sav
piedomains/model/calibrate/text/jobsearch.sav
piedomains/model/calibrate/text/models.sav
piedomains/model/calibrate/text/movies.sav
piedomains/model/calibrate/text/music.sav
piedomains/model/calibrate/text/news.sav
piedomains/model/calibrate/text/politics.sav
piedomains/model/calibrate/text/porn.sav
piedomains/model/calibrate/text/radiotv.sav
piedomains/model/calibrate/text/recreation.sav
piedomains/model/calibrate/text/redirector.sav
piedomains/model/calibrate/text/religion.sav
piedomains/model/calibrate/text/science.sav
piedomains/model/calibrate/text/searchengines.sav
piedomains/model/calibrate/text/sex.sav
piedomains-0.5.0.dist-info/METADATA
piedomains-0.5.0.dist-info/WHEEL
piedomains-0.5.0.dist-info/entry_points.txt
piedomains-0.5.0.dist-info/licenses/LICENSE
piedomains-0.5.0.dist-info/RECORD
