Metadata-Version: 2.4
Name: piedomains
Version: 0.5.0
Summary: Predict categories based on domain names and their content
Project-URL: Homepage, https://github.com/themains/piedomains
Project-URL: Documentation, https://themains.github.io/piedomains/
Project-URL: Repository, https://github.com/themains/piedomains
Project-URL: Issues, https://github.com/themains/piedomains/issues
Project-URL: Changelog, https://github.com/themains/piedomains/blob/main/CHANGELOG.md
Author-email: Rajashekar Chintalapati <rajshekar.ch@gmail.com>, Gaurav Sood <gsood07@gmail.com>
License: MIT License
License-File: LICENSE
Keywords: computer vision,content analysis,domain classification,machine learning,web scraping,website categorization
Classifier: Development Status :: 4 - Beta
Classifier: Intended Audience :: Developers
Classifier: Intended Audience :: Science/Research
Classifier: License :: OSI Approved :: MIT License
Classifier: Programming Language :: Python :: 3.11
Classifier: Programming Language :: Python :: 3.12
Classifier: Programming Language :: Python :: 3.13
Classifier: Topic :: Internet :: WWW/HTTP
Classifier: Topic :: Scientific/Engineering :: Information Analysis
Classifier: Topic :: Software Development :: Libraries :: Python Modules
Classifier: Topic :: Text Processing :: Markup :: HTML
Classifier: Topic :: Utilities
Requires-Python: <3.14,>=3.11
Requires-Dist: beautifulsoup4>=4.10.0
Requires-Dist: joblib>=1.2.0
Requires-Dist: litellm>=1.55.0
Requires-Dist: nltk>=3.8
Requires-Dist: numpy>=1.24.0
Requires-Dist: pandas>=2.0.0
Requires-Dist: pillow>=10.0.0
Requires-Dist: playwright>=1.40.0
Requires-Dist: requests>=2.25.0
Requires-Dist: scikit-learn>=1.3.0
Requires-Dist: tensorflow>=2.12.0
Requires-Dist: tqdm>=4.64.0
Provides-Extra: dev
Requires-Dist: black>=24.0; extra == 'dev'
Requires-Dist: isort>=5.0; extra == 'dev'
Requires-Dist: mypy>=1.0; extra == 'dev'
Requires-Dist: pre-commit>=3.0; extra == 'dev'
Requires-Dist: psutil>=5.9.0; extra == 'dev'
Requires-Dist: pytest-cov>=4.0; extra == 'dev'
Requires-Dist: pytest-mock>=3.10; extra == 'dev'
Requires-Dist: pytest-xdist>=3.0; extra == 'dev'
Requires-Dist: pytest>=7.0; extra == 'dev'
Requires-Dist: ruff>=0.7.0; extra == 'dev'
Provides-Extra: docs
Requires-Dist: furo>=2024.1.29; extra == 'docs'
Requires-Dist: myst-parser>=2.0; extra == 'docs'
Requires-Dist: sphinx-autodoc-typehints>=1.25; extra == 'docs'
Requires-Dist: sphinx-copybutton>=0.5; extra == 'docs'
Requires-Dist: sphinx>=7.0; extra == 'docs'
Provides-Extra: test
Requires-Dist: psutil>=5.9.0; extra == 'test'
Requires-Dist: pytest-cov>=4.0; extra == 'test'
Requires-Dist: pytest-mock>=3.10; extra == 'test'
Requires-Dist: pytest>=7.0; extra == 'test'
Requires-Dist: ruff>=0.7.0; extra == 'test'
